mx2/__init__.py
mx2/enums.py
mx2/exceptions.py
mx2/types.py
tests/__init__.py
tests/inverter.py
tests/modbus.py
tests/ser.py
tests/types.py
pymx2-0.1.6.dist-info/LICENSE
pymx2-0.1.6.dist-info/METADATA
pymx2-0.1.6.dist-info/WHEEL
pymx2-0.1.6.dist-info/top_level.txt
pymx2-0.1.6.dist-info/RECORD
