Metadata-Version: 2.1
Name: pymx2
Version: 0.1.6
Summary: A Python driver to communicate with an Omron MX2 inverter through Modbus
Home-page: https://github.com/vpaeder/pymx2
Author: Vincent Paeder
Author-email: python@paeder.fi
Project-URL: Bug Tracker, https://github.com/vpaeder/pymx2/issues
Keywords: omron,mx2,inverter
Classifier: Development Status :: 5 - Production/Stable
Classifier: Programming Language :: Python :: 3
Classifier: License :: OSI Approved :: MIT License
Classifier: Operating System :: OS Independent
Classifier: Intended Audience :: Developers
Classifier: Topic :: Communications
Classifier: Topic :: System :: Hardware :: Hardware Drivers
Requires-Python: >=3.9
License-File: LICENSE
Requires-Dist: pyserial
